asciivmssdashboard/__init__.py
asciivmssdashboard/azure.py
asciivmssdashboard/console.py
asciivmssdashboard/datacenters.py
asciivmssdashboard/demo.py
asciivmssdashboard/includes.py
asciivmssdashboard/logtail.py
asciivmssdashboard/maps.py
asciivmssdashboard/unicurses.py
asciivmssdashboard/windows.py
asciivmssdashboard/pdc34dll/curses.h
asciivmssdashboard/pdc34dll/panel.h
asciivmssdashboard/pdc34dll/pdcurses.dll
asciivmssdashboard/pdc34dll/pdcurses.lib
asciivmssdashboard/pdc34dll/pdcurses32.dll
asciivmssdashboard/pdc34dll/pdcurses64.dll
asciivmssdashboard-2.0.2.data/scripts/asciivmssdashboard
asciivmssdashboard-2.0.2.dist-info/LICENSE.txt
asciivmssdashboard-2.0.2.dist-info/METADATA
asciivmssdashboard-2.0.2.dist-info/WHEEL
asciivmssdashboard-2.0.2.dist-info/top_level.txt
asciivmssdashboard-2.0.2.dist-info/RECORD
