Metadata-Version: 1.0
Name: asciivmssdashboard
Version: 2.0.2
Summary: Terminal Based Dashboard to view and manage Azure VM Scale Sets.
Home-page: http://github.com/msleal/asciivmssdashboard
Author: msleal
Author-email: msl@eall.com.br
License: MIT
Keywords: ascii terminal vmss scale dashboard azure virtual curses graphical interface
Platform: UNKNOWN
